cyborg_tempest_plugin/__init__.py
cyborg_tempest_plugin/config.py
cyborg_tempest_plugin/plugin.py
cyborg_tempest_plugin/services/__init__.py
cyborg_tempest_plugin/services/cyborg_data.py
cyborg_tempest_plugin/services/cyborg_rest_client.py
cyborg_tempest_plugin/tests/__init__.py
cyborg_tempest_plugin/tests/api/__init__.py
cyborg_tempest_plugin/tests/api/base.py
cyborg_tempest_plugin/tests/api/test_accelerator_request.py
cyborg_tempest_plugin/tests/api/test_accelerator_request_negative.py
cyborg_tempest_plugin/tests/api/test_deployable_negative.py
cyborg_tempest_plugin/tests/api/test_deployables.py
cyborg_tempest_plugin/tests/api/test_device.py
cyborg_tempest_plugin/tests/api/test_device_negative.py
cyborg_tempest_plugin/tests/api/test_device_profile.py
cyborg_tempest_plugin/tests/api/test_device_profile_negative.py
cyborg_tempest_plugin/tests/scenario/__init__.py
cyborg_tempest_plugin/tests/scenario/manager.py
cyborg_tempest_plugin/tests/scenario/test_accelerator_basic_ops.py
cyborg_tempest_plugin-2.6.0.dist-info/AUTHORS
cyborg_tempest_plugin-2.6.0.dist-info/LICENSE
cyborg_tempest_plugin-2.6.0.dist-info/METADATA
cyborg_tempest_plugin-2.6.0.dist-info/WHEEL
cyborg_tempest_plugin-2.6.0.dist-info/entry_points.txt
cyborg_tempest_plugin-2.6.0.dist-info/pbr.json
cyborg_tempest_plugin-2.6.0.dist-info/top_level.txt
cyborg_tempest_plugin-2.6.0.dist-info/RECORD
